[{"id": 19, "type": "METHOD", "children": [20, 21, 99, 100, 101], "value": "public static void main(String[] a) throws IOException"}, {"id": 20, "type": "METHOD_PARAMETER_IN", "value": "String[] a"}, {"id": 21, "type": "BLOCK", "children": [4, 22, 25, 36, 37], "value": "<empty>"}, {"id": 4, "type": "LOCAL", "value": "BufferedReader input"}, {"id": 22, "type": "CALL", "children": [23, 24], "value": "ANY input = new BufferedReader(new InputStreamReader(System.in))"}, {"id": 23, "type": "IDENTIFIER", "value": "input"}, {"id": 24, "type": "CALL", "value": "new BufferedReader(new InputStreamReader(System.in))"}, {"id": 25, "type": "CALL", "children": [3, 26], "value": "new BufferedReader(new InputStreamReader(System.in))"}, {"id": 3, "type": "IDENTIFIER", "value": "input"}, {"id": 26, "type": "BLOCK", "children": [27, 30, 35], "value": "<empty>"}, {"id": 27, "type": "CALL", "children": [28, 29], "value": "<empty>"}, {"id": 28, "type": "IDENTIFIER", "value": "$obj0"}, {"id": 29, "type": "CALL", "value": "new InputStreamReader(System.in)"}, {"id": 30, "type": "CALL", "children": [31, 32], "value": "new InputStreamReader(System.in)"}, {"id": 31, "type": "IDENTIFIER", "value": "$obj0"}, {"id": 32, "type": "CALL", "children": [33, 34], "value": "System.in"}, {"id": 33, "type": "IDENTIFIER", "value": "System"}, {"id": 34, "type": "FIELD_IDENTIFIER", "value": "in"}, {"id": 35, "type": "IDENTIFIER", "value": "$obj0"}, {"id": 36, "type": "LOCAL", "value": "String s"}, {"id": 37, "type": "CONTROL_STRUCTURE", "children": [38, 44], "value": "while ((s = input.readLine()) != null)"}, {"id": 38, "type": "CALL", "children": [39, 43], "value": "(s = input.readLine()) != null"}, {"id": 39, "type": "CALL", "children": [40, 41], "value": "s = readLine()"}, {"id": 40, "type": "IDENTIFIER", "value": "s"}, {"id": 41, "type": "CALL", "children": [42], "value": "readLine()"}, {"id": 42, "type": "IDENTIFIER", "value": "input"}, {"id": 43, "type": "LITERAL", "value": "null"}, {"id": 44, "type": "BLOCK", "children": [45, 46, 52, 53, 60, 61, 68], "value": "<empty>"}, {"id": 45, "type": "LOCAL", "value": "String[] num"}, {"id": 46, "type": "CALL", "children": [47, 48], "value": "String[] num = s.split(\" \", 0)"}, {"id": 47, "type": "IDENTIFIER", "value": "num"}, {"id": 48, "type": "CALL", "children": [49, 50, 51], "value": "s.split(\" \", 0)"}, {"id": 49, "type": "IDENTIFIER", "value": "s"}, {"id": 50, "type": "LITERAL", "value": "\" \""}, {"id": 51, "type": "LITERAL", "value": "0"}, {"id": 52, "type": "LOCAL", "value": "int x"}, {"id": 53, "type": "CALL", "children": [54, 55], "value": "int x = parseInt(num[0])"}, {"id": 54, "type": "IDENTIFIER", "value": "x"}, {"id": 55, "type": "CALL", "children": [56, 57], "value": "parseInt(num[0])"}, {"id": 56, "type": "IDENTIFIER", "value": "this"}, {"id": 57, "type": "CALL", "children": [58, 59], "value": "num[0]"}, {"id": 58, "type": "IDENTIFIER", "value": "num"}, {"id": 59, "type": "LITERAL", "value": "0"}, {"id": 60, "type": "LOCAL", "value": "int y"}, {"id": 61, "type": "CALL", "children": [62, 63], "value": "int y = parseInt(num[1])"}, {"id": 62, "type": "IDENTIFIER", "value": "y"}, {"id": 63, "type": "CALL", "children": [64, 65], "value": "parseInt(num[1])"}, {"id": 64, "type": "IDENTIFIER", "value": "this"}, {"id": 65, "type": "CALL", "children": [66, 67], "value": "num[1]"}, {"id": 66, "type": "IDENTIFIER", "value": "num"}, {"id": 67, "type": "LITERAL", "value": "1"}, {"id": 68, "type": "CONTROL_STRUCTURE", "children": [69, 84], "value": "if (0 <= x && x <= 1000000 && 0 <= y && y <= 1000000)"}, {"id": 69, "type": "CALL", "children": [70, 81], "value": "0 <= x && x <= 1000000 && 0 <= y && y <= 1000000"}, {"id": 70, "type": "CALL", "children": [71, 78], "value": "0 <= x && x <= 1000000 && 0 <= y"}, {"id": 71, "type": "CALL", "children": [72, 75], "value": "0 <= x && x <= 1000000"}, {"id": 72, "type": "CALL", "children": [73, 74], "value": "0 <= x"}, {"id": 73, "type": "LITERAL", "value": "0"}, {"id": 74, "type": "IDENTIFIER", "value": "x"}, {"id": 75, "type": "CALL", "children": [76, 77], "value": "x <= 1000000"}, {"id": 76, "type": "IDENTIFIER", "value": "x"}, {"id": 77, "type": "LITERAL", "value": "1000000"}, {"id": 78, "type": "CALL", "children": [79, 80], "value": "0 <= y"}, {"id": 79, "type": "LITERAL", "value": "0"}, {"id": 80, "type": "IDENTIFIER", "value": "y"}, {"id": 81, "type": "CALL", "children": [82, 83], "value": "y <= 1000000"}, {"id": 82, "type": "IDENTIFIER", "value": "y"}, {"id": 83, "type": "LITERAL", "value": "1000000"}, {"id": 84, "type": "BLOCK", "children": [85, 86, 91], "value": "<empty>"}, {"id": 85, "type": "LOCAL", "value": "int z"}, {"id": 86, "type": "CALL", "children": [87, 88], "value": "int z = x + y"}, {"id": 87, "type": "IDENTIFIER", "value": "z"}, {"id": 88, "type": "CALL", "children": [89, 90], "value": "x + y"}, {"id": 89, "type": "IDENTIFIER", "value": "x"}, {"id": 90, "type": "IDENTIFIER", "value": "y"}, {"id": 91, "type": "CALL", "children": [92, 95], "value": "System.out.println(Integer.toString(z).length())"}, {"id": 92, "type": "CALL", "children": [93, 94], "value": "System.out"}, {"id": 93, "type": "IDENTIFIER", "value": "System"}, {"id": 94, "type": "FIELD_IDENTIFIER", "value": "out"}, {"id": 95, "type": "CALL", "children": [96], "value": "Integer.toString(z).length()"}, {"id": 96, "type": "CALL", "children": [97, 98], "value": "Integer.toString(z)"}, {"id": 97, "type": "IDENTIFIER", "value": "Integer"}, {"id": 98, "type": "IDENTIFIER", "value": "z"}, {"id": 99, "type": "MODIFIER", "value": "<empty>"}, {"id": 100, "type": "MODIFIER", "value": "<empty>"}, {"id": 101, "type": "METHOD_RETURN", "value": "RET"}]
